magicauth/__init__.py
magicauth/admin.py
magicauth/apps.py
magicauth/forms.py
magicauth/models.py
magicauth/next_url.py
magicauth/otp_forms.py
magicauth/send_token.py
magicauth/settings.py
magicauth/urls.py
magicauth/utils.py
magicauth/views.py
magicauth/migrations/0001_initial.py
magicauth/migrations/__init__.py
magicauth/templates/magicauth/email.html
magicauth/templates/magicauth/email.txt
magicauth/templates/magicauth/email_sent.html
magicauth/templates/magicauth/login.html
magicauth/templates/magicauth/wait.html
tests/__init__.py
tests/factories.py
tests/test_1_GET_login_view.py
tests/test_2_POST_login_view.py
tests/test_3_email_sent_view.py
tests/test_4_wait_view.py
tests/test_5_validate_token_view.py
tests/test_settings.py
tests/test_url.py
django_magicauth-1.0.2.dist-info/LICENSE
django_magicauth-1.0.2.dist-info/METADATA
django_magicauth-1.0.2.dist-info/WHEEL
django_magicauth-1.0.2.dist-info/top_level.txt
django_magicauth-1.0.2.dist-info/RECORD
