Metadata-Version: 2.1
Name: django-magicauth
Version: 1.0.2
Summary: Password-less authentication: login by clicking on a magic link received by email.
Home-page: 
Author: 
Author-email: 
Classifier: Environment :: Web Environment
Classifier: Framework :: Django
Classifier: Intended Audience :: Developers
Classifier: License :: OSI Approved :: MIT License
Classifier: Operating System :: OS Independent
Classifier: Programming Language :: Python
Classifier: Programming Language :: Python
Classifier: Topic :: Internet :: WWW/HTTP
Classifier: Topic :: Internet :: WWW/HTTP :: Dynamic Content
License-File: LICENSE
